AFTSA/__init__.py
AFTSA/intervals.py
AFTSA/randoms.py
AFTSA-1.0.9.dist-info/LICENSE
AFTSA-1.0.9.dist-info/METADATA
AFTSA-1.0.9.dist-info/WHEEL
AFTSA-1.0.9.dist-info/top_level.txt
AFTSA-1.0.9.dist-info/RECORD
