Metadata-Version: 2.1
Name: AFTSA
Version: 1.0.9
Summary: A package for creating evenly distributed and randomized, non overlapping rfc3339 timestamps for conducting statistical time series analysis using your API of choice.
Author-email: Colby Eagan <colbyeagan6@gmail.com>
License: BSD 3-Clause License
Project-URL: Homepage, https://github.com/colbyeagan/AFTSA
Classifier: Programming Language :: Python :: 3.11
Classifier: License :: OSI Approved :: BSD License
Classifier: Operating System :: OS Independent
Requires-Python: >=3.11
License-File: LICENSE
Requires-Dist: datetime >=5.2
Requires-Dist: rfc3339-validator ==0.1.4
Requires-Dist: rfc3986-validator ==0.1.1
Requires-Dist: python-dateutil ==2.8.2
